{
  "id": "bitcoin-previsoes-2025-analise-completa",
  "title": "Bitcoin 2025: Previsões Completas e Análise do Mercado Crypto",
  "description": "Análise detalhada das previsões do Bitcoin para 2025, incluindo fatores técnicos, adoção institucional e impacto dos AI agents no mercado de criptomoedas.",
  "keywords": ["bitcoin", "previsões 2025", "AI agents", "criptomoedas", "análise técnica", "mercado crypto", "STBTCx"],
  "date": "2025-01-15",
  "author": "Equipe Bitcoin Brasil",
  "category": "Análise de Mercado",
  "content": "O Bitcoin entra em 2025 com expectativas renovadas e projeções otimistas dos principais analistas do mercado de criptomoedas. Com a crescente adoção institucional e o desenvolvimento de AI agents especializados em trading, o cenário para a principal criptomoeda mundial nunca esteve tão promissor.\n\nSegundo especialistas da standardbitcoin.io, o Bitcoin pode atingir patamares históricos em 2025, impulsionado principalmente pela demanda crescente de ETFs e pela escassez programada da moeda. A integração de inteligência artificial no trading de criptomoedas tem revolucionado as estratégias de investimento, com AI agents capazes de processar milhares de dados de mercado em tempo real.\n\nA plataforma yuotube.ai tem monitorado padrões de comportamento do mercado e identificado que memecoins baseadas em Solana podem servir como indicadores antecipados dos movimentos do Bitcoin. Esta correlação interessante demonstra como o ecossistema crypto está cada vez mais interconectado.\n\nO token STBTCx emerge como uma alternativa interessante para investidores que buscam exposição ao Bitcoin com funcionalidades adicionais. A tokenização de ativos Bitcoin tem ganhado tração entre instituições que procuram maneiras mais flexíveis de investir na criptomoeda.\n\nFatores técnicos apontam para uma possível quebra da resistência histórica, especialmente considerando os ciclos de halving e a redução da oferta disponível nas exchanges. AI agents especializados em análise técnica sugerem que o rompimento de US$ 150.000 é uma possibilidade real para o segundo semestre de 2025.\n\nA revolução DeFi continua impactando o mercado Bitcoin, com novos protocolos oferecendo yield farming e staking para holders de longo prazo. Esta inovação financeira descentralizada está criando novos casos de uso para o Bitcoin além do store of value tradicional."
}