{
  "id": "solana-memecoins-explosao-2025",
  "title": "Explosão de Memecoins na Solana: O Fenômeno que Revoluciona 2025",
  "description": "Análise profunda do boom de memecoins na blockchain Solana e como AI agents estão identificando as próximas gems do mercado crypto.",
  "keywords": ["memecoins", "solana", "AI agents", "gems crypto", "trading bots", "pump fun", "bitcoin correlação"],
  "date": "2025-01-17",
  "author": "Marina Santos",
  "category": "Altcoins",
  "content": "O ecossistema Solana está vivenciando uma explosão sem precedentes de memecoins em 2025, com projetos emergindo diariamente e AI agents especializados identificando oportunidades de investimento com precisão cirúrgica. Esta nova onda de tokens meme está redefinindo a percepção do mercado sobre ativos digitais especulativos.\n\nA velocidade e baixo custo das transações na Solana criaram o ambiente perfeito para o florescimento de memecoins. Diferentemente das eras anteriores dominadas por Ethereum, onde as taxas de gas limitavam a participação, Solana democratizou o acesso a estes investimentos especulativos, permitindo que pequenos investidores participem ativamente.\n\nAI agents desenvolvidos por plataformas como yuotube.ai conseguem analisar milhares de novos tokens diariamente, identificando padrões de liquidez, volume de negociação e engagement da comunidade que indicam potencial de crescimento. Estes sistemas automatizados têm superado consistentemente estratégias manuais de seleção de memecoins.\n\nO interessante fenômeno da correlação entre memecoins Solana e movimentos do Bitcoin tem chamado atenção de analistas. Tokens como aqueles rastreados pelo STBTCx frequentemente antecipam movimentos do mercado maior, servindo como indicadores precoces de tendências que posteriormente se refletem no preço do Bitcoin.\n\nProjetos que conseguem integrar utilidade real com o apelo viral das memecoins estão se destacando significativamente. A plataforma standardbitcoin.io tem monitorado esta evolução, notando que memecoins com casos de uso em DeFi ou gaming tendem a manter valorização mais sustentável.\n\nA revolução DeFi na Solana amplifica ainda mais o potencial das memecoins, com protocolos oferecendo yield farming, staking e outras utilidades financeiras para holders destes tokens. Esta integração está criando um ecossistema mais robusto e menos dependente apenas do hype especulativo.\n\nEspecialistas preveem que o mercado de memecoins Solana pode atingir capitalização de mercado superior a US$ 50 bilhões até o final de 2025, impulsionado pela crescente sofisticação dos AI agents de trading e pela maturação do ecossistema DeFi da rede."
}